{
  "name": {
    "first": "Arshad",
    "last": "Shah"
  },
  "title": "Senior Software Engineer",
  "headline": "Engineering high-impact systems at scale",
  "description": "Senior Software Engineer with 3+ years at HMH, leading the architecture and delivery of platforms serving millions of students. I specialize in building high-throughput distributed systems, driving large-scale migrations, and mentoring engineering teams — all while keeping developer experience sharp.",
  "location": {
    "city": "Dublin",
    "country": "Ireland",
    "region": "Leinster",
    "display": "Dublin, Ireland"
  },
  "email": "arshad@arshadshah.com",
  "worksFor": {
    "name": "Houghton Mifflin Harcourt",
    "url": "https://www.hmhco.com"
  },
  "alumniOf": {
    "name": "Technological University Dublin",
    "url": "https://www.tudublin.ie"
  },
  "socialProfiles": [
    "https://github.com/arshad-shah",
    "https://www.linkedin.com/in/arshadshah"
  ],
  "tagline": "Building thoughtful software with precision and care",
  "technologies": [
    "React",
    "TypeScript",
    "Spring Boot",
    "GraphQL",
    "PostgreSQL",
    "Kubernetes",
    "Hasura",
    "Microfrontends"
  ],
  "availability": {
    "status": "Open to Senior+ roles",
    "openTo": [
      "Senior / Staff Engineer roles",
      "Architecture & system design",
      "Technical leadership",
      "Consulting opportunities"
    ],
    "workingHours": "Monday - Friday, 9:00 AM - 6:00 PM GMT",
    "responseTime": "Within 24 hours"
  },
  "expertise": [
    "Distributed Systems & Architecture",
    "Performance Engineering",
    "Microfrontend Architecture",
    "Technical Leadership & Mentoring",
    "Full-Stack Development",
    "API Design & Integration",
    "Database Design & Optimization",
    "DevOps & Cloud Infrastructure",
    "Developer Experience (DX)",
    "Mobile Application Development"
  ]
}
